<?xml version="1.0" encoding="utf-8"?>
<level xmlns:xsi="http://www.w3.org/2001/XMLSchema-instance" xmlns:xsd="http://www.w3.org/2001/XMLSchema">
	<name>Level 6</name>
	<description> </description>
	<tileset>TilesetWorld3</tileset>
	<world width="16" height="14">
0000 0000 0000 0143 0061 0061 0061 0061 0144 0068 0072 0072 0074 0000 0000 0000 
0000 0000 0000 0062 0641 0641 0449 0449 0114 0449 0449 0449 0073 0072 0074 0000 
0000 0000 0000 0062 0641 0641 0449 0449 0449 0449 0449 0449 0067 0244 0067 0000 
0000 0000 0000 0062 0641 0641 0449 0449 0112 0449 0449 0073 0072 0072 0074 0000 
0000 0000 0067 0146 0061 0061 0061 0061 0145 0449 0449 0066 0449 0449 0068 0074 
0073 0072 0074 0449 0449 0449 0449 0449 0449 0449 0449 0449 0449 0449 0449 0067 
0067 0213 0067 0449 0449 0067 0449 0449 0068 0074 0449 0449 0067 0449 0449 0067 
0073 0072 0072 0069 0449 0068 0074 0449 0449 0070 0075 0072 0074 0449 0068 0074 
0067 0449 0449 0449 0449 0449 0068 0072 0072 0072 0074 0449 0066 0449 0449 0067 
0067 0449 0066 0449 0449 0449 0449 0449 0449 0449 0067 0449 0449 0449 0449 0067 
0067 0449 0449 0449 0449 0449 0449 0449 0449 0449 0067 0449 0449 0449 0073 0069 
0068 0072 0072 0074 0449 0068 0069 0449 0073 0072 0072 0072 0072 0072 0069 0000 
0000 0000 0000 0067 0449 0449 0449 0449 0067 0000 0000 0000 0000 0000 0000 0000 
0000 0000 0000 0068 0072 0072 0072 0072 0069 0000 0000 0000 0000 0000 0000 0000 
</world>
	<entities>
		<entity type="box" x="3" y="8" />
		<entity type="box" x="4" y="9" />
		<entity type="box" x="7" y="9" />
		<entity type="box" x="12" y="9" />
		<entity type="player" x="2" y="10" />
		<entity type="box" x="3" y="10" />
		<entity type="box" x="6" y="10" />
	</entities>
</level>