<?xml version="1.0" encoding="utf-8"?>
<level xmlns:xsi="http://www.w3.org/2001/XMLSchema-instance" xmlns:xsd="http://www.w3.org/2001/XMLSchema">
	<name>Level 1</name>
	<description> </description>
	<tileset>TilesetWorld9</tileset>
	<world width="20" height="12">
0137 0136 0136 0136 0136 0133 0111 0061 0061 0061 0061 0144 0132 0136 0136 0136 0140 0139 0136 0138 
0131 0256 0256 0256 0256 0256 0256 0640 0640 0640 0640 0114 0256 0256 0256 0256 0132 0133 0193 0131 
0131 0256 0256 0256 0256 0256 0256 0640 0640 0640 0640 0256 0256 0256 0256 0256 0256 0256 0256 0130 
0131 0256 0131 0256 0132 0133 0111 0061 0061 0061 0061 0113 0132 0133 0256 0256 0256 0256 0256 0112 
0131 0256 0130 0256 0256 0256 0256 0131 0256 0256 0256 0256 0256 0256 0132 0133 0112 0640 0640 0062 
0131 0256 0256 0256 0256 0256 0256 0130 0256 0256 0132 0136 0133 0256 0256 0256 0062 0640 0640 0062 
0131 0256 0256 0256 0137 0136 0133 0256 0256 0256 0256 0256 0256 0256 0256 0256 0062 0640 0640 0062 
0131 0256 0256 0256 0130 0256 0256 0256 0256 0256 0256 0256 0130 0256 0256 0130 0114 0640 0640 0062 
0131 0256 0256 0131 0256 0256 0256 0256 0256 0130 0256 0256 0256 0132 0133 0256 0256 0256 0111 0145 
0131 0256 0132 0133 0256 0256 0130 0256 0256 0256 0256 0256 0256 0256 0256 0256 0256 0256 0132 0138 
0134 0135 0256 0256 0256 0256 0256 0256 0256 0134 0135 0256 0256 0256 0131 0256 0256 0131 0225 0131 
0132 0136 0136 0136 0136 0136 0136 0136 0136 0136 0136 0136 0136 0136 0136 0136 0136 0136 0136 0133 
</world>
	<entities>
		<entity type="box" x="3" y="4" />
		<entity type="box" x="3" y="5" />
		<entity type="box" x="8" y="5" />
		<entity type="box" x="9" y="5" />
		<entity type="box" x="2" y="6" />
		<entity type="box" x="8" y="6" />
		<entity type="box" x="12" y="6" />
		<entity type="box" x="2" y="7" />
		<entity type="box" x="8" y="7" />
		<entity type="box" x="10" y="7" />
		<entity type="box" x="6" y="8" />
		<entity type="box" x="7" y="8" />
		<entity type="box" x="11" y="8" />
		<entity type="player" x="1" y="9" />
		<entity type="box" x="5" y="9" />
		<entity type="box" x="9" y="9" />
		<entity type="box" x="12" y="9" />
	</entities>
</level>